bfloat/__init__.py
bfloat/client.py
bfloat/constants.py
bfloat/exceptions.py
bfloat/models.py
bfloat-1.0.3.dist-info/METADATA
bfloat-1.0.3.dist-info/WHEEL
bfloat-1.0.3.dist-info/top_level.txt
bfloat-1.0.3.dist-info/RECORD
