Metadata-Version: 2.1
Name: bfloat
Version: 1.0.3
Summary: A Python SDK for interacting with the bfloat.ai API
Home-page: https://github.com/bfloat-ai/python-sdk
Author: Edison Abahurire
Author-email: edison@bfloat.ai
Classifier: Development Status :: 5 - Production/Stable
Classifier: Intended Audience :: Developers
Classifier: License :: OSI Approved :: MIT License
Classifier: Operating System :: OS Independent
Classifier: Programming Language :: Python :: 3
Classifier: Programming Language :: Python :: 3.8
Classifier: Programming Language :: Python :: 3.9
Classifier: Programming Language :: Python :: 3.10
Classifier: Programming Language :: Python :: 3.11
Classifier: Topic :: Software Development :: Libraries :: Python Modules
Classifier: Topic :: Internet :: WWW/HTTP
Classifier: Typing :: Typed
Requires-Python: >=3.8
Requires-Dist: aiohttp >=3.8.0
Requires-Dist: typing-extensions >=4.5.0
Requires-Dist: requests >=2.26.0
Provides-Extra: dev
Requires-Dist: pytest >=7.3.1 ; extra == 'dev'
Requires-Dist: pytest-asyncio >=0.21.0 ; extra == 'dev'
Requires-Dist: pytest-cov >=4.1.0 ; extra == 'dev'
Requires-Dist: black >=23.7.0 ; extra == 'dev'
Requires-Dist: isort >=5.12.0 ; extra == 'dev'
Requires-Dist: mypy >=1.4.1 ; extra == 'dev'
Requires-Dist: pdoc >=14.0.0 ; extra == 'dev'
